hdr_random/__init__.py
hdr_random/_modidx.py
hdr_random/core.py
hdr_random-0.0.4.dist-info/LICENSE
hdr_random-0.0.4.dist-info/METADATA
hdr_random-0.0.4.dist-info/WHEEL
hdr_random-0.0.4.dist-info/entry_points.txt
hdr_random-0.0.4.dist-info/top_level.txt
hdr_random-0.0.4.dist-info/RECORD
